swagger2jsonschema/__init__.py
swagger2jsonschema/command.py
swagger2jsonschema/definitions.py
swagger2jsonschema/errors.py
swagger2jsonschema/log.py
swagger2jsonschema/test_command.py
swagger2jsonschema/util.py
swagger2jsonschema-0.1.2.dist-info/LICENSE
swagger2jsonschema-0.1.2.dist-info/METADATA
swagger2jsonschema-0.1.2.dist-info/WHEEL
swagger2jsonschema-0.1.2.dist-info/entry_points.txt
swagger2jsonschema-0.1.2.dist-info/top_level.txt
swagger2jsonschema-0.1.2.dist-info/RECORD
